saneround/__init__.py
saneround/py.typed
saneround/saneround.py
saneround-0.1.2.dist-info/LICENSE
saneround-0.1.2.dist-info/METADATA
saneround-0.1.2.dist-info/WHEEL
saneround-0.1.2.dist-info/top_level.txt
saneround-0.1.2.dist-info/RECORD
