Metadata-Version: 2.1
Name: saneround
Version: 0.1.2
Summary: Python package providing sane round() instead of official insane round().
Home-page: https://github.com/yamaimo/saneround
Author: yamaimo
Author-email: hello@yamaimo.dev
License: MIT License
License-File: LICENSE
Provides-Extra: develop
Requires-Dist: pysen[lint] ; extra == 'develop'
